akvo_weather_info-0.2.0.dist-info/licenses/LICENSE
weather/__init__.py
weather/__main__.py
weather/cli.py
weather/config.py
weather/models.py
weather/py.typed
weather/formatters/__init__.py
weather/formatters/json_formatter.py
weather/formatters/raw_formatter.py
weather/formatters/text_formatter.py
weather/services/__init__.py
weather/services/base.py
weather/services/openweathermap.py
weather/services/weatherapi.py
akvo_weather_info-0.2.0.dist-info/METADATA
akvo_weather_info-0.2.0.dist-info/WHEEL
akvo_weather_info-0.2.0.dist-info/entry_points.txt
akvo_weather_info-0.2.0.dist-info/top_level.txt
akvo_weather_info-0.2.0.dist-info/RECORD
