Metadata-Version: 2.4
Name: akvo-weather-info
Version: 0.2.0
Summary: Python library to fetch weather data from multiple providers
Author-email: Deden Bangkit <deden@akvo.org>
Maintainer: Akvo
License: AGPL-3.0
Project-URL: Homepage, https://github.com/akvo/weather-info
Project-URL: Repository, https://github.com/akvo/weather-info
Project-URL: Issues, https://github.com/akvo/weather-info/issues
Keywords: weather,openweathermap,weatherapi,forecast,climate
Classifier: Development Status :: 4 - Beta
Classifier: Intended Audience :: Developers
Classifier: License :: OSI Approved :: GNU Affero General Public License v3
Classifier: Operating System :: OS Independent
Classifier: Programming Language :: Python :: 3
Classifier: Programming Language :: Python :: 3.10
Classifier: Programming Language :: Python :: 3.11
Classifier: Programming Language :: Python :: 3.12
Classifier: Topic :: Scientific/Engineering :: Atmospheric Science
Classifier: Topic :: Software Development :: Libraries :: Python Modules
Classifier: Typing :: Typed
Requires-Python: >=3.10
License-File: LICENSE
Requires-Dist: httpx>=0.27.0
Requires-Dist: python-dotenv>=1.0.0
Provides-Extra: dev
Requires-Dist: pytest>=7.0.0; extra == "dev"
Requires-Dist: build>=1.0.0; extra == "dev"
Requires-Dist: twine>=4.0.0; extra == "dev"
Dynamic: license-file
